xontrib_cd/__init__.py
xontrib_cd/event_hooks.py
xontrib_cd/helper.py
xontrib_cd/main.py
xontrib_cd-0.3.1.dist-info/METADATA
xontrib_cd-0.3.1.dist-info/WHEEL
xontrib_cd-0.3.1.dist-info/entry_points.txt
xontrib_cd-0.3.1.dist-info/RECORD
